examples/__init__.py
examples/analysis_example.py
examples/enhance_example.py
examples/mastering_example.py
examples/mix_example.py
roex_mcp/__init__.py
roex_mcp/client.py
roex_mcp/controllers/__init__.py
roex_mcp/controllers/analysis_controller.py
roex_mcp/controllers/enhance_controller.py
roex_mcp/controllers/mastering_controller.py
roex_mcp/controllers/mix_controller.py
roex_mcp/models/__init__.py
roex_mcp/models/analysis.py
roex_mcp/models/common.py
roex_mcp/models/enhance.py
roex_mcp/models/mastering.py
roex_mcp/models/mixing.py
roex_mcp/providers/__init__.py
roex_mcp/providers/api_provider.py
roex_mcp-0.1.0.dist-info/licenses/LICENSE
roex_mcp-0.1.0.dist-info/METADATA
roex_mcp-0.1.0.dist-info/WHEEL
roex_mcp-0.1.0.dist-info/top_level.txt
roex_mcp-0.1.0.dist-info/RECORD
