Metadata-Version: 2.4
Name: roex-mcp
Version: 0.1.0
Summary: MCP (Model-Controller-Provider) client for the RoEx Tonn API
Home-page: https://github.com/roexaudio/roex-mcp
Author: RoEx Audio
Author-email: support@roexaudio.com
Classifier: Programming Language :: Python :: 3
Classifier: License :: OSI Approved :: MIT License
Classifier: Operating System :: OS Independent
Requires-Python: >=3.7
License-File: LICENSE
Requires-Dist: requests>=2.25.0
Dynamic: author
Dynamic: author-email
Dynamic: classifier
Dynamic: description
Dynamic: description-content-type
Dynamic: home-page
Dynamic: license-file
Dynamic: requires-dist
Dynamic: requires-python
Dynamic: summary
